selenium_auto_refresh/__init__.py
selenium_auto_refresh/refresher.py
selenium_auto_refresh-1.1.0.dist-info/licenses/LICENSE
selenium_auto_refresh-1.1.0.dist-info/METADATA
selenium_auto_refresh-1.1.0.dist-info/WHEEL
selenium_auto_refresh-1.1.0.dist-info/top_level.txt
selenium_auto_refresh-1.1.0.dist-info/RECORD
