Metadata-Version: 2.4
Name: selenium-auto-refresh
Version: 1.1.0
Summary: Automatically refresh Selenium Chrome tabs at specified intervals
Home-page: https://github.com/Lalit2206/selenium-auto-refresh
Author: Lalit2206
Author-email: Lalit Pal <happytaak8@gmail.com>
License: MIT
Project-URL: Homepage, https://github.com/Lalit2206/selenium-auto-refresh.git
Project-URL: Repository, https://github.com/Lalit2206/selenium-auto-refresh.git
Project-URL: Issues, https://github.com/Lalit2206/selenium-auto-refresh.git
Keywords: selenium,chrome,refresh,automation,testing,webdriver
Classifier: Development Status :: 4 - Beta
Classifier: Intended Audience :: Developers
Classifier: Topic :: Software Development :: Testing
Classifier: License :: OSI Approved :: MIT License
Classifier: Programming Language :: Python :: 3
Requires-Python: >=3.7
License-File: LICENSE
Dynamic: author
Dynamic: home-page
Dynamic: license-file
Dynamic: requires-python
